{
  "capabilities": [
    "configurable"
  ],
  "appKeys": {
    "KEY_DECODE": 0,
    "KEY_LANG": 1,
    "KEY_VIBES": 2,
    "weather": 3,
    "interval": 4,
    "gps": 5,
    "location": 6,
    "units": 7,
    "icon": 8,
    "temperature": 9
  },
  "resources": {
    "media": [
        {
            "type": "png",
            "menuIcon": true,
            "name": "IMAGE_MENU_ICON",
            "file": "images/logo.png"
        },
        {
          "type": "png",
          "name": "EXAMPLE_IMAGE",
          "file": "images/example-image.png"
        },
      {
        "type": "png",
        "name": "WEATHER00",
        "file": "images/0.png"
      },
      {
        "type": "png",
        "name": "WEATHER01",
        "file": "images/1.png"
      },
      {
        "type": "png",
        "name": "WEATHER02",
        "file": "images/2.png"
      },
      {
        "type": "png",
        "name": "WEATHER03",
        "file": "images/3.png"
      },
      {
        "type": "png",
        "name": "WEATHER04",
        "file": "images/4.png"
      },
      {
        "type": "png",
        "name": "WEATHER05",
        "file": "images/5.png"
      },
      {
        "type": "png",
        "name": "WEATHER06",
        "file": "images/6.png"
      },
      {
        "type": "png",
        "name": "WEATHER07",
        "file": "images/7.png"
      },
      {
        "type": "png",
        "name": "WEATHER08",
        "file": "images/8.png"
      },
      {
        "type": "png",
        "name": "WEATHER09",
        "file": "images/9.png"
      },
      {
        "type": "png",
        "name": "WEATHER10",
        "file": "images/10.png"
      },
      {
        "type": "png",
        "name": "WEATHER11",
        "file": "images/11.png"
      },
      {
        "type": "png",
        "name": "WEATHER12",
        "file": "images/12.png"
      },
      {
        "type": "png",
        "name": "WEATHER13",
        "file": "images/13.png"
      },
      {
        "type": "png",
        "name": "WEATHER14",
        "file": "images/14.png"
      },
      {
        "type": "png",
        "name": "WEATHER15",
        "file": "images/15.png"
      },
      {
        "type": "png",
        "name": "WEATHER16",
        "file": "images/16.png"
      },
      {
        "type": "png",
        "name": "WEATHER17",
        "file": "images/17.png"
      },
      {
        "type": "png",
        "name": "WEATHER18",
        "file": "images/18.png"
      },
      {
        "type": "png",
        "name": "WEATHER19",
        "file": "images/19.png"
      },
      {
        "type": "png",
        "name": "WEATHER20",
        "file": "images/20.png"
      },
      {
        "type": "png",
        "name": "WEATHER21",
        "file": "images/21.png"
      },
      {
        "type": "png",
        "name": "WEATHER22",
        "file": "images/22.png"
      },
      {
        "type": "png",
        "name": "WEATHER23",
        "file": "images/23.png"
      },
      {
        "type": "png",
        "name": "WEATHER24",
        "file": "images/24.png"
      },
      {
        "type": "png",
        "name": "WEATHER25",
        "file": "images/25.png"
      },
      {
        "type": "png",
        "name": "WEATHER26",
        "file": "images/26.png"
      },
      {
        "type": "png",
        "name": "WEATHER27",
        "file": "images/27.png"
      },
      {
        "type": "png",
        "name": "WEATHER28",
        "file": "images/28.png"
      },
      {
        "type": "png",
        "name": "WEATHER29",
        "file": "images/29.png"
      },
      {
        "type": "png",
        "name": "WEATHER30",
        "file": "images/30.png"
      },
      {
        "type": "png",
        "name": "WEATHER31",
        "file": "images/31.png"
      },
      {
        "type": "png",
        "name": "WEATHER32",
        "file": "images/32.png"
      },
      {
        "type": "png",
        "name": "WEATHER33",
        "file": "images/33.png"
      },
      {
        "type": "png",
        "name": "WEATHER34",
        "file": "images/34.png"
      },
      {
        "type": "png",
        "name": "WEATHER35",
        "file": "images/35.png"
      },
      {
        "type": "png",
        "name": "WEATHER36",
        "file": "images/36.png"
      },
      {
        "type": "png",
        "name": "WEATHER37",
        "file": "images/37.png"
      },
      {
        "type": "png",
        "name": "WEATHER38",
        "file": "images/38.png"
      },
      {
        "type": "png",
        "name": "WEATHER39",
        "file": "images/39.png"
      },
      {
        "type": "png",
        "name": "WEATHER40",
        "file": "images/40.png"
      },
      {
        "type": "png",
        "name": "WEATHER41",
        "file": "images/41.png"
      },
      {
        "type": "png",
        "name": "WEATHER42",
        "file": "images/42.png"
      },
      {
        "type": "png",
        "name": "WEATHER43",
        "file": "images/43.png"
      },
      {
        "type": "png",
        "name": "WEATHER44",
        "file": "images/44.png"
      },
      {
        "type": "png",
        "name": "WEATHER45",
        "file": "images/45.png"
      },
      {
        "type": "png",
        "name": "WEATHER46",
        "file": "images/46.png"
      },
      {
        "type": "png",
        "name": "WEATHER47",
        "file": "images/47.png"
      },
      {
        "type": "png",
        "name": "WEATHERNA",
        "file": "images/3200.png"
      }
        ,{
            "characterRegex": "[0-9 ]",
            "type": "font",
            "name": "FONT_CUSTOMA_42",
            "file": "fonts/klingon font.ttf"
        }
        ,{
            "characterRegex": "[MONTUEWDHFRISA]",
            "type": "font",
            "name": "FONT_CUSTOMA_30",
            "file": "fonts/klingon font.ttf"
        }
        ,{
            "characterRegex": "[0-9 ]",
            "type": "font",
            "name": "FONT_CUSTOMB_42",
            "file": "fonts/Aurebesh Cantina Bold.otf"
        }
        ,{
            "characterRegex": "[MONTUEWDHFRISA]",
            "type": "font",
            "name": "FONT_CUSTOMB_30",
            "file": "fonts/Aurebesh Cantina Bold.otf"
        }
        ,{
            "characterRegex": "[0-9 ]",
            "type": "font",
            "name": "FONT_CUSTOMC_42",
            "file": "fonts/Aurek-Besh Hand.ttf"
        }
        ,{
            "characterRegex": "[MONTUEWDHFRISA]",
            "type": "font",
            "name": "FONT_CUSTOMC_30",
            "file": "fonts/Aurek-Besh Hand.ttf"
        }
        ,{
            "characterRegex": "[0-9 ]",
            "type": "font",
            "name": "FONT_CUSTOMD_42",
            "file": "fonts/Graalen.ttf"
        }
        ,{
            "characterRegex": "[MONTUEWDHFRISA]",
            "type": "font",
            "name": "FONT_CUSTOMD_30",
            "file": "fonts/Graalen.ttf"
        }
        ,{
            "characterRegex": "[0-9 ]",
            "type": "font",
            "name": "FONT_CUSTOME_42",
            "file": "fonts/Kentaurus.otf"
        }
        ,{
            "characterRegex": "[MONTUEWDHFRISA]",
            "type": "font",
            "name": "FONT_CUSTOME_30",
            "file": "fonts/Kentaurus.otf"
        }
        ,{
            "characterRegex": "[0-9 ]",
            "type": "font",
            "name": "FONT_CUSTOMF_42",
            "file": "fonts/mandalor.ttf"
        }
        ,{
            "characterRegex": "[MONTUEWDHFRISA]",
            "type": "font",
            "name": "FONT_CUSTOMF_30",
            "file": "fonts/mandalor.ttf"
        }
        ,{
            "characterRegex": "[0-9 ]",
            "type": "font",
            "name": "FONT_CUSTOMG_42",
            "file": "fonts/Betazed-Bold.ttf"
        }
        ,{
            "characterRegex": "[MONTUEWDHFRISA]",
            "type": "font",
            "name": "FONT_CUSTOMG_30",
            "file": "fonts/Betazed-Bold.ttf"
        }
    ]
  },
  "shortName": "Enigma Rosetta",
  "longName": "Enigma Rosetta (Digital, Color) Watch Face",
  "versionCode": 2,
  "companyName": "neon",
  "versionLabel": "2.3",
  "uuid": "ecc8f112-318f-4ef2-be11-53c63f8af13f",
  "watchapp": {
    "watchface": true
  },
  "targetPlatforms": [
    "basalt"
  ],
  "sdkVersion": "3"
}

